[
    {
        "stops": "Nonstop",
        "ticket price": "173.30",
        "flight duration": "0 days 1 hours 33 minutes",
        "airline": "American Airlines",
        "plane": "Embraer RJ145",
        "timings": [
            {
                "departure_airport": "New York, NY (LGA-LaGuardia)",
                "departure_time": "8:35pm",
                "arrival_airport": "Montreal, QC, Canada (YUL-Pierre Elliott Trudeau Intl.)",
                "arrival_time": "10:08pm"
            }
        ],
        "plane code": "ER4"
    },
    {
        "stops": "Nonstop",
        "ticket price": "173.30",
        "flight duration": "0 days 1 hours 32 minutes",
        "airline": "American Airlines",
        "plane": "Embraer RJ145",
        "timings": [
            {
                "departure_airport": "New York, NY (LGA-LaGuardia)",
                "departure_time": "11:05am",
                "arrival_airport": "Montreal, QC, Canada (YUL-Pierre Elliott Trudeau Intl.)",
                "arrival_time": "12:37pm"
            }
        ],
        "plane code": "ER4"
    },
    {
        "stops": "Nonstop",
        "ticket price": "173.30",
        "flight duration": "0 days 1 hours 26 minutes",
        "airline": "American Airlines",
        "plane": "Embraer RJ145",
        "timings": [
            {
                "departure_airport": "New York, NY (LGA-LaGuardia)",
                "departure_time": "8:00am",
                "arrival_airport": "Montreal, QC, Canada (YUL-Pierre Elliott Trudeau Intl.)",
                "arrival_time": "9:26am"
            }
        ],
        "plane code": "ER4"
    },
    {
        "stops": "Nonstop",
        "ticket price": "173.30",
        "flight duration": "0 days 1 hours 31 minutes",
        "airline": "American Airlines",
        "plane": "Embraer RJ145",
        "timings": [
            {
                "departure_airport": "New York, NY (LGA-LaGuardia)",
                "departure_time": "3:25pm",
                "arrival_airport": "Montreal, QC, Canada (YUL-Pierre Elliott Trudeau Intl.)",
                "arrival_time": "4:56pm"
            }
        ],
        "plane code": "ER4"
    },
    {
        "stops": "1 Stop",
        "ticket price": "181.90",
        "flight duration": "0 days 5 hours 38 minutes",
        "airline": "American Airlines",
        "plane": "Embraer RJ145",
        "timings": [
            {
                "departure_airport": "New York, NY (LGA-LaGuardia)",
                "departure_time": "2:55pm",
                "arrival_airport": "Philadelphia, PA (PHL-Philadelphia Intl.)",
                "arrival_time": "4:03pm"
            },
            {
                "departure_airport": "Philadelphia, PA (PHL-Philadelphia Intl.)",
                "departure_time": "6:45pm",
                "arrival_airport": "Montreal, QC, Canada (YUL-Pierre Elliott Trudeau Intl.)",
                "arrival_time": "8:33pm"
            }
        ],
        "plane code": "ER4"
    },
    {
        "stops": "1 Stop",
        "ticket price": "181.90",
        "flight duration": "0 days 4 hours 45 minutes",
        "airline": "American Airlines",
        "plane": "Embraer RJ145",
        "timings": [
            {
                "departure_airport": "New York, NY (LGA-LaGuardia)",
                "departure_time": "11:00am",
                "arrival_airport": "Philadelphia, PA (PHL-Philadelphia Intl.)",
                "arrival_time": "12:13pm"
            },
            {
                "departure_airport": "Philadelphia, PA (PHL-Philadelphia Intl.)",
                "departure_time": "2:05pm",
                "arrival_airport": "Montreal, QC, Canada (YUL-Pierre Elliott Trudeau Intl.)",
                "arrival_time": "3:45pm"
            }
        ],
        "plane code": "ER4"
    },
    {
        "stops": "Nonstop",
        "ticket price": "187.30",
        "flight duration": "0 days 1 hours 41 minutes",
        "airline": "WestJet",
        "plane": "Canadair RJ",
        "timings": [
            {
                "departure_airport": "New York, NY (JFK-John F. Kennedy Intl.)",
                "departure_time": "8:55pm",
                "arrival_airport": "Montreal, QC, Canada (YUL-Pierre Elliott Trudeau Intl.)",
                "arrival_time": "10:36pm"
            }
        ],
        "plane code": "CRJ"
    },
    {
        "stops": "Nonstop",
        "ticket price": "187.30",
        "flight duration": "0 days 1 hours 41 minutes",
        "airline": "WestJet",
        "plane": "Canadian Regional Jet 700",
        "timings": [
            {
                "departure_airport": "New York, NY (LGA-LaGuardia)",
                "departure_time": "8:25am",
                "arrival_airport": "Montreal, QC, Canada (YUL-Pierre Elliott Trudeau Intl.)",
                "arrival_time": "10:06am"
            }
        ],
        "plane code": "CR7"
    },
    {
        "stops": "Nonstop",
        "ticket price": "187.30",
        "flight duration": "0 days 1 hours 30 minutes",
        "airline": "WestJet",
        "plane": "Canadian Regional Jet 700",
        "timings": [
            {
                "departure_airport": "New York, NY (LGA-LaGuardia)",
                "departure_time": "8:26pm",
                "arrival_airport": "Montreal, QC, Canada (YUL-Pierre Elliott Trudeau Intl.)",
                "arrival_time": "9:56pm"
            }
        ],
        "plane code": "CR7"
    },
    {
        "stops": "Nonstop",
        "ticket price": "187.30",
        "flight duration": "0 days 1 hours 38 minutes",
        "airline": "WestJet",
        "plane": "Canadair RJ",
        "timings": [
            {
                "departure_airport": "New York, NY (JFK-John F. Kennedy Intl.)",
                "departure_time": "9:40am",
                "arrival_airport": "Montreal, QC, Canada (YUL-Pierre Elliott Trudeau Intl.)",
                "arrival_time": "11:18am"
            }
        ],
        "plane code": "CRJ"
    },
    {
        "stops": "Nonstop",
        "ticket price": "191.60",
        "flight duration": "0 days 1 hours 38 minutes",
        "airline": "Delta",
        "plane": "Canadair RJ",
        "timings": [
            {
                "departure_airport": "New York, NY (JFK-John F. Kennedy Intl.)",
                "departure_time": "9:40am",
                "arrival_airport": "Montreal, QC, Canada (YUL-Pierre Elliott Trudeau Intl.)",
                "arrival_time": "11:18am"
            }
        ],
        "plane code": "CRJ"
    },
    {
        "stops": "Nonstop",
        "ticket price": "191.60",
        "flight duration": "0 days 1 hours 45 minutes",
        "airline": "Delta",
        "plane": "",
        "timings": [
            {
                "departure_airport": "New York, NY (JFK-John F. Kennedy Intl.)",
                "departure_time": "3:55pm",
                "arrival_airport": "Montreal, QC, Canada (YUL-Pierre Elliott Trudeau Intl.)",
                "arrival_time": "5:40pm"
            }
        ],
        "plane code": ""
    },
    {
        "stops": "Nonstop",
        "ticket price": "191.60",
        "flight duration": "0 days 1 hours 41 minutes",
        "airline": "Delta",
        "plane": "Canadian Regional Jet 700",
        "timings": [
            {
                "departure_airport": "New York, NY (LGA-LaGuardia)",
                "departure_time": "8:25am",
                "arrival_airport": "Montreal, QC, Canada (YUL-Pierre Elliott Trudeau Intl.)",
                "arrival_time": "10:06am"
            }
        ],
        "plane code": "CR7"
    },
    {
        "stops": "Nonstop",
        "ticket price": "191.60",
        "flight duration": "0 days 1 hours 41 minutes",
        "airline": "Delta",
        "plane": "Canadair RJ",
        "timings": [
            {
                "departure_airport": "New York, NY (JFK-John F. Kennedy Intl.)",
                "departure_time": "8:55pm",
                "arrival_airport": "Montreal, QC, Canada (YUL-Pierre Elliott Trudeau Intl.)",
                "arrival_time": "10:36pm"
            }
        ],
        "plane code": "CRJ"
    },
    {
        "stops": "Nonstop",
        "ticket price": "191.60",
        "flight duration": "0 days 1 hours 44 minutes",
        "airline": "Delta",
        "plane": "",
        "timings": [
            {
                "departure_airport": "New York, NY (LGA-LaGuardia)",
                "departure_time": "10:29am",
                "arrival_airport": "Montreal, QC, Canada (YUL-Pierre Elliott Trudeau Intl.)",
                "arrival_time": "12:13pm"
            }
        ],
        "plane code": ""
    },
    {
        "stops": "Nonstop",
        "ticket price": "191.60",
        "flight duration": "0 days 1 hours 30 minutes",
        "airline": "Delta",
        "plane": "Canadian Regional Jet 700",
        "timings": [
            {
                "departure_airport": "New York, NY (LGA-LaGuardia)",
                "departure_time": "8:26pm",
                "arrival_airport": "Montreal, QC, Canada (YUL-Pierre Elliott Trudeau Intl.)",
                "arrival_time": "9:56pm"
            }
        ],
        "plane code": "CR7"
    },
    {
        "stops": "Nonstop",
        "ticket price": "191.60",
        "flight duration": "0 days 1 hours 37 minutes",
        "airline": "Delta",
        "plane": "",
        "timings": [
            {
                "departure_airport": "New York, NY (LGA-LaGuardia)",
                "departure_time": "2:29pm",
                "arrival_airport": "Montreal, QC, Canada (YUL-Pierre Elliott Trudeau Intl.)",
                "arrival_time": "4:06pm"
            }
        ],
        "plane code": ""
    },
    {
        "stops": "Nonstop",
        "ticket price": "200.20",
        "flight duration": "0 days 1 hours 25 minutes",
        "airline": "United",
        "plane": "Embraer 175",
        "timings": [
            {
                "departure_airport": "New York, NY (LGA-LaGuardia)",
                "departure_time": "6:40am",
                "arrival_airport": "Montreal, QC, Canada (YUL-Pierre Elliott Trudeau Intl.)",
                "arrival_time": "8:05am"
            }
        ],
        "plane code": "E75"
    },
    {
        "stops": "Nonstop",
        "ticket price": "200.20",
        "flight duration": "0 days 1 hours 25 minutes",
        "airline": "Air Canada",
        "plane": "Embraer 175",
        "timings": [
            {
                "departure_airport": "New York, NY (LGA-LaGuardia)",
                "departure_time": "6:40am",
                "arrival_airport": "Montreal, QC, Canada (YUL-Pierre Elliott Trudeau Intl.)",
                "arrival_time": "8:05am"
            }
        ],
        "plane code": "E75"
    },
    {
        "stops": "1 Stop",
        "ticket price": "208.80",
        "flight duration": "0 days 4 hours 12 minutes",
        "airline": "United",
        "plane": "Canadian Regional Jet 700",
        "timings": [
            {
                "departure_airport": "New York, NY (LGA-LaGuardia)",
                "departure_time": "6:00am",
                "arrival_airport": "Washington, DC (IAD-Washington Dulles Intl.)",
                "arrival_time": "7:33am"
            },
            {
                "departure_airport": "Washington, DC (IAD-Washington Dulles Intl.)",
                "departure_time": "8:30am",
                "arrival_airport": "Montreal, QC, Canada (YUL-Pierre Elliott Trudeau Intl.)",
                "arrival_time": "10:12am"
            }
        ],
        "plane code": "CR7"
    }
]