[
    {
        "arrival": {
            "airportCode": "GIG", 
            "airportCity": "Rio de Janeiro"
        }, 
        "travel_date": "03/15/18", 
        "flight duration": "1 days 20 hours 40 minutes", 
        "plane": "Airbus A320", 
        "stops": "2 Stops", 
        "total_distance": "5,334 miles", 
        "plane code": "320", 
        "booking_date": "12/18/17", 
        "departure": {
            "airportCode": "JFK", 
            "airportCity": "New York"
        }, 
        "timings": [
            {
                "arrival_airport": "Cartagena, Colombia (CTG-Rafael Nunez Intl.)", 
                "arrival_time": "12:59pm", 
                "departure_airport": "New York, NY (JFK-John F. Kennedy Intl.)", 
                "departure_time": "7:55am"
            }, 
            {
                "arrival_airport": "Bogota, Colombia (BOG-El Dorado Intl.)", 
                "arrival_time": "6:29pm", 
                "departure_airport": "Cartagena, Colombia (CTG-Rafael Nunez Intl.)", 
                "departure_time": "5:00pm"
            }, 
            {
                "arrival_airport": "Rio de Janeiro, Brazil (GIG-Galeao - Antonio Carlos Jobim Intl.)", 
                "arrival_time": "7:35am", 
                "departure_airport": "Bogota, Colombia (BOG-El Dorado Intl.)", 
                "departure_time": "10:18pm"
            }
        ], 
        "ticket price": "1268.90", 
        "airline": "", 
        "carrier_operatedby": ""
    }, 
    {
        "arrival": {
            "airportCode": "GIG", 
            "airportCity": "Rio de Janeiro"
        }, 
        "travel_date": "03/15/18", 
        "flight duration": "1 days 20 hours 40 minutes", 
        "plane": "Airbus A320", 
        "stops": "2 Stops", 
        "total_distance": "5,334 miles", 
        "plane code": "320", 
        "booking_date": "12/18/17", 
        "departure": {
            "airportCode": "JFK", 
            "airportCity": "New York"
        }, 
        "timings": [
            {
                "arrival_airport": "Cartagena, Colombia (CTG-Rafael Nunez Intl.)", 
                "arrival_time": "12:59pm", 
                "departure_airport": "New York, NY (JFK-John F. Kennedy Intl.)", 
                "departure_time": "7:55am"
            }, 
            {
                "arrival_airport": "Bogota, Colombia (BOG-El Dorado Intl.)", 
                "arrival_time": "7:24pm", 
                "departure_airport": "Cartagena, Colombia (CTG-Rafael Nunez Intl.)", 
                "departure_time": "5:57pm"
            }, 
            {
                "arrival_airport": "Rio de Janeiro, Brazil (GIG-Galeao - Antonio Carlos Jobim Intl.)", 
                "arrival_time": "7:35am", 
                "departure_airport": "Bogota, Colombia (BOG-El Dorado Intl.)", 
                "departure_time": "10:18pm"
            }
        ], 
        "ticket price": "1268.90", 
        "airline": "", 
        "carrier_operatedby": ""
    }, 
    {
        "arrival": {
            "airportCode": "GIG", 
            "airportCity": "Rio de Janeiro"
        }, 
        "travel_date": "03/15/18", 
        "flight duration": "1 days 17 hours 25 minutes", 
        "plane": "AIRBUS INDUSTRIE A330-200", 
        "stops": "1 Stops", 
        "total_distance": "4,989 miles", 
        "plane code": "332", 
        "booking_date": "12/18/17", 
        "departure": {
            "airportCode": "JFK", 
            "airportCity": "New York"
        }, 
        "timings": [
            {
                "arrival_airport": "Sao Paulo, Brazil (GRU-Guarulhos - Governor Andre Franco Montoro Intl.)", 
                "arrival_time": "12:30pm", 
                "departure_airport": "New York, NY (JFK-John F. Kennedy Intl.)", 
                "departure_time": "11:30pm"
            }, 
            {
                "arrival_airport": "Rio de Janeiro, Brazil (GIG-Galeao - Antonio Carlos Jobim Intl.)", 
                "arrival_time": "7:55pm", 
                "departure_airport": "Sao Paulo, Brazil (GRU-Guarulhos - Governor Andre Franco Montoro Intl.)", 
                "departure_time": "6:45pm"
            }
        ], 
        "ticket price": "1303.22", 
        "airline": "Avianca Brasil", 
        "carrier_operatedby": ""
    }, 
    {
        "arrival": {
            "airportCode": "GIG", 
            "airportCity": "Rio de Janeiro"
        }, 
        "travel_date": "03/15/18", 
        "flight duration": "1 days 21 hours 15 minutes", 
        "plane": "AIRBUS INDUSTRIE A330-200", 
        "stops": "1 Stops", 
        "total_distance": "4,989 miles", 
        "plane code": "332", 
        "booking_date": "12/18/17", 
        "departure": {
            "airportCode": "JFK", 
            "airportCity": "New York"
        }, 
        "timings": [
            {
                "arrival_airport": "Sao Paulo, Brazil (GRU-Guarulhos - Governor Andre Franco Montoro Intl.)", 
                "arrival_time": "12:30pm", 
                "departure_airport": "New York, NY (JFK-John F. Kennedy Intl.)", 
                "departure_time": "11:30pm"
            }, 
            {
                "arrival_airport": "Rio de Janeiro, Brazil (GIG-Galeao - Antonio Carlos Jobim Intl.)", 
                "arrival_time": "11:45pm", 
                "departure_airport": "Sao Paulo, Brazil (GRU-Guarulhos - Governor Andre Franco Montoro Intl.)", 
                "departure_time": "10:35pm"
            }
        ], 
        "ticket price": "1303.22", 
        "airline": "Avianca Brasil", 
        "carrier_operatedby": ""
    }, 
    {
        "arrival": {
            "airportCode": "GIG", 
            "airportCity": "Rio de Janeiro"
        }, 
        "travel_date": "03/15/18", 
        "flight duration": "1 days 17 hours 40 minutes", 
        "plane": "AIRBUS INDUSTRIE A330-200", 
        "stops": "2 Stops", 
        "total_distance": "5,555 miles", 
        "plane code": "332", 
        "booking_date": "12/18/17", 
        "departure": {
            "airportCode": "JFK", 
            "airportCity": "New York"
        }, 
        "timings": [
            {
                "arrival_airport": "Sao Paulo, Brazil (GRU-Guarulhos - Governor Andre Franco Montoro Intl.)", 
                "arrival_time": "12:30pm", 
                "departure_airport": "New York, NY (JFK-John F. Kennedy Intl.)", 
                "departure_time": "11:30pm"
            }, 
            {
                "arrival_airport": "Florianopolis, Brazil (FLN-Hercilio Luz Intl.)", 
                "arrival_time": "6:02pm", 
                "departure_airport": "Sao Paulo, Brazil (GRU-Guarulhos - Governor Andre Franco Montoro Intl.)", 
                "departure_time": "4:40pm"
            }, 
            {
                "arrival_airport": "Rio de Janeiro, Brazil (GIG-Galeao - Antonio Carlos Jobim Intl.)", 
                "arrival_time": "8:10pm", 
                "departure_airport": "Florianopolis, Brazil (FLN-Hercilio Luz Intl.)", 
                "departure_time": "6:35pm"
            }
        ], 
        "ticket price": "1309.87", 
        "airline": "Avianca Brasil", 
        "carrier_operatedby": ""
    }, 
    {
        "arrival": {
            "airportCode": "SDU", 
            "airportCity": "Rio de Janeiro"
        }, 
        "travel_date": "03/15/18", 
        "flight duration": "1 days 18 hours 35 minutes", 
        "plane": "Embraer 175", 
        "stops": "2 Stops", 
        "total_distance": "5,639 miles", 
        "plane code": "E75", 
        "booking_date": "12/18/17", 
        "departure": {
            "airportCode": "EWR", 
            "airportCity": "Newark"
        }, 
        "timings": [
            {
                "arrival_airport": "Toronto, ON, Canada (YYZ-Pearson Intl.)", 
                "arrival_time": "7:37pm", 
                "departure_airport": "Newark, NJ (EWR-Liberty Intl.)", 
                "departure_time": "6:05pm"
            }, 
            {
                "arrival_airport": "Sao Paulo, Brazil (GRU-Guarulhos - Governor Andre Franco Montoro Intl.)", 
                "arrival_time": "12:30pm", 
                "departure_airport": "Toronto, ON, Canada (YYZ-Pearson Intl.)", 
                "departure_time": "11:25pm"
            }, 
            {
                "arrival_airport": "Rio de Janeiro, Brazil (SDU-Santos Dumont)", 
                "arrival_time": "3:40pm", 
                "departure_airport": "Sao Paulo, Brazil (GRU-Guarulhos - Governor Andre Franco Montoro Intl.)", 
                "departure_time": "2:35pm"
            }
        ], 
        "ticket price": "1485.53", 
        "airline": "Air Canada", 
        "carrier_operatedby": "Air Canada Express - Sky Regional"
    }, 
    {
        "arrival": {
            "airportCode": "SDU", 
            "airportCity": "Rio de Janeiro"
        }, 
        "travel_date": "03/15/18", 
        "flight duration": "1 days 16 hours 0 minutes", 
        "plane": "Embraer 175", 
        "stops": "2 Stops", 
        "total_distance": "5,639 miles", 
        "plane code": "E75", 
        "booking_date": "12/18/17", 
        "departure": {
            "airportCode": "EWR", 
            "airportCity": "Newark"
        }, 
        "timings": [
            {
                "arrival_airport": "Toronto, ON, Canada (YYZ-Pearson Intl.)", 
                "arrival_time": "10:12pm", 
                "departure_airport": "Newark, NJ (EWR-Liberty Intl.)", 
                "departure_time": "8:40pm"
            }, 
            {
                "arrival_airport": "Sao Paulo, Brazil (GRU-Guarulhos - Governor Andre Franco Montoro Intl.)", 
                "arrival_time": "12:30pm", 
                "departure_airport": "Toronto, ON, Canada (YYZ-Pearson Intl.)", 
                "departure_time": "11:25pm"
            }, 
            {
                "arrival_airport": "Rio de Janeiro, Brazil (SDU-Santos Dumont)", 
                "arrival_time": "3:40pm", 
                "departure_airport": "Sao Paulo, Brazil (GRU-Guarulhos - Governor Andre Franco Montoro Intl.)", 
                "departure_time": "2:35pm"
            }
        ], 
        "ticket price": "1485.53", 
        "airline": "Air Canada", 
        "carrier_operatedby": "Air Canada Express - Sky Regional"
    }, 
    {
        "arrival": {
            "airportCode": "SDU", 
            "airportCity": "Rio de Janeiro"
        }, 
        "travel_date": "03/15/18", 
        "flight duration": "1 days 21 hours 20 minutes", 
        "plane": "Embraer 175", 
        "stops": "2 Stops", 
        "total_distance": "5,639 miles", 
        "plane code": "E75", 
        "booking_date": "12/18/17", 
        "departure": {
            "airportCode": "EWR", 
            "airportCity": "Newark"
        }, 
        "timings": [
            {
                "arrival_airport": "Toronto, ON, Canada (YYZ-Pearson Intl.)", 
                "arrival_time": "7:37pm", 
                "departure_airport": "Newark, NJ (EWR-Liberty Intl.)", 
                "departure_time": "6:05pm"
            }, 
            {
                "arrival_airport": "Sao Paulo, Brazil (GRU-Guarulhos - Governor Andre Franco Montoro Intl.)", 
                "arrival_time": "12:30pm", 
                "departure_airport": "Toronto, ON, Canada (YYZ-Pearson Intl.)", 
                "departure_time": "11:25pm"
            }, 
            {
                "arrival_airport": "Rio de Janeiro, Brazil (SDU-Santos Dumont)", 
                "arrival_time": "6:25pm", 
                "departure_airport": "Sao Paulo, Brazil (GRU-Guarulhos - Governor Andre Franco Montoro Intl.)", 
                "departure_time": "5:25pm"
            }
        ], 
        "ticket price": "1485.53", 
        "airline": "Air Canada", 
        "carrier_operatedby": "Air Canada Express - Sky Regional"
    }, 
    {
        "arrival": {
            "airportCode": "SDU", 
            "airportCity": "Rio de Janeiro"
        }, 
        "travel_date": "03/15/18", 
        "flight duration": "1 days 18 hours 45 minutes", 
        "plane": "Embraer 175", 
        "stops": "2 Stops", 
        "total_distance": "5,639 miles", 
        "plane code": "E75", 
        "booking_date": "12/18/17", 
        "departure": {
            "airportCode": "EWR", 
            "airportCity": "Newark"
        }, 
        "timings": [
            {
                "arrival_airport": "Toronto, ON, Canada (YYZ-Pearson Intl.)", 
                "arrival_time": "10:12pm", 
                "departure_airport": "Newark, NJ (EWR-Liberty Intl.)", 
                "departure_time": "8:40pm"
            }, 
            {
                "arrival_airport": "Sao Paulo, Brazil (GRU-Guarulhos - Governor Andre Franco Montoro Intl.)", 
                "arrival_time": "12:30pm", 
                "departure_airport": "Toronto, ON, Canada (YYZ-Pearson Intl.)", 
                "departure_time": "11:25pm"
            }, 
            {
                "arrival_airport": "Rio de Janeiro, Brazil (SDU-Santos Dumont)", 
                "arrival_time": "6:25pm", 
                "departure_airport": "Sao Paulo, Brazil (GRU-Guarulhos - Governor Andre Franco Montoro Intl.)", 
                "departure_time": "5:25pm"
            }
        ], 
        "ticket price": "1485.53", 
        "airline": "Air Canada", 
        "carrier_operatedby": "Air Canada Express - Sky Regional"
    }, 
    {
        "arrival": {
            "airportCode": "GIG", 
            "airportCity": "Rio de Janeiro"
        }, 
        "travel_date": "03/15/18", 
        "flight duration": "1 days 13 hours 45 minutes", 
        "plane": "Boeing 737-900", 
        "stops": "1 Stops", 
        "total_distance": "5,519 miles", 
        "plane code": "739", 
        "booking_date": "12/18/17", 
        "departure": {
            "airportCode": "EWR", 
            "airportCity": "Newark"
        }, 
        "timings": [
            {
                "arrival_airport": "Panama City, Panama (PTY-Tocumen Intl.)", 
                "arrival_time": "8:05pm", 
                "departure_airport": "Newark, NJ (EWR-Liberty Intl.)", 
                "departure_time": "2:50pm"
            }, 
            {
                "arrival_airport": "Rio de Janeiro, Brazil (GIG-Galeao - Antonio Carlos Jobim Intl.)", 
                "arrival_time": "7:35am", 
                "departure_airport": "Panama City, Panama (PTY-Tocumen Intl.)", 
                "departure_time": "9:28pm"
            }
        ], 
        "ticket price": "1514.35", 
        "airline": "Copa", 
        "carrier_operatedby": "United"
    }, 
    {
        "arrival": {
            "airportCode": "GIG", 
            "airportCity": "Rio de Janeiro"
        }, 
        "travel_date": "03/15/18", 
        "flight duration": "1 days 18 hours 29 minutes", 
        "plane": "Airbus A320", 
        "stops": "2 Stops", 
        "total_distance": "5,554 miles", 
        "plane code": "320", 
        "booking_date": "12/18/17", 
        "departure": {
            "airportCode": "EWR", 
            "airportCity": "Newark"
        }, 
        "timings": [
            {
                "arrival_airport": "Fort Lauderdale, FL (FLL-Fort Lauderdale - Hollywood Intl.)", 
                "arrival_time": "1:17pm", 
                "departure_airport": "Newark, NJ (EWR-Liberty Intl.)", 
                "departure_time": "10:06am"
            }, 
            {
                "arrival_airport": "Panama City, Panama (PTY-Tocumen Intl.)", 
                "arrival_time": "8:27pm", 
                "departure_airport": "Fort Lauderdale, FL (FLL-Fort Lauderdale - Hollywood Intl.)", 
                "departure_time": "5:16pm"
            }, 
            {
                "arrival_airport": "Rio de Janeiro, Brazil (GIG-Galeao - Antonio Carlos Jobim Intl.)", 
                "arrival_time": "7:35am", 
                "departure_airport": "Panama City, Panama (PTY-Tocumen Intl.)", 
                "departure_time": "9:28pm"
            }
        ], 
        "ticket price": "1525.85", 
        "airline": "", 
        "carrier_operatedby": ""
    }, 
    {
        "arrival": {
            "airportCode": "SDU", 
            "airportCity": "Rio de Janeiro"
        }, 
        "travel_date": "03/15/18", 
        "flight duration": "1 days 17 hours 35 minutes", 
        "plane": "Airbus A319", 
        "stops": "2 Stops", 
        "total_distance": "5,639 miles", 
        "plane code": "319", 
        "booking_date": "12/18/17", 
        "departure": {
            "airportCode": "LGA", 
            "airportCity": "New York"
        }, 
        "timings": [
            {
                "arrival_airport": "Toronto, ON, Canada (YYZ-Pearson Intl.)", 
                "arrival_time": "8:40pm", 
                "departure_airport": "New York, NY (LGA-LaGuardia)", 
                "departure_time": "7:05pm"
            }, 
            {
                "arrival_airport": "Sao Paulo, Brazil (GRU-Guarulhos - Governor Andre Franco Montoro Intl.)", 
                "arrival_time": "12:30pm", 
                "departure_airport": "Toronto, ON, Canada (YYZ-Pearson Intl.)", 
                "departure_time": "11:25pm"
            }, 
            {
                "arrival_airport": "Rio de Janeiro, Brazil (SDU-Santos Dumont)", 
                "arrival_time": "3:40pm", 
                "departure_airport": "Sao Paulo, Brazil (GRU-Guarulhos - Governor Andre Franco Montoro Intl.)", 
                "departure_time": "2:35pm"
            }
        ], 
        "ticket price": "1655.53", 
        "airline": "", 
        "carrier_operatedby": ""
    }, 
    {
        "arrival": {
            "airportCode": "SDU", 
            "airportCity": "Rio de Janeiro"
        }, 
        "travel_date": "03/15/18", 
        "flight duration": "1 days 20 hours 20 minutes", 
        "plane": "Airbus A319", 
        "stops": "2 Stops", 
        "total_distance": "5,639 miles", 
        "plane code": "319", 
        "booking_date": "12/18/17", 
        "departure": {
            "airportCode": "LGA", 
            "airportCity": "New York"
        }, 
        "timings": [
            {
                "arrival_airport": "Toronto, ON, Canada (YYZ-Pearson Intl.)", 
                "arrival_time": "8:40pm", 
                "departure_airport": "New York, NY (LGA-LaGuardia)", 
                "departure_time": "7:05pm"
            }, 
            {
                "arrival_airport": "Sao Paulo, Brazil (GRU-Guarulhos - Governor Andre Franco Montoro Intl.)", 
                "arrival_time": "12:30pm", 
                "departure_airport": "Toronto, ON, Canada (YYZ-Pearson Intl.)", 
                "departure_time": "11:25pm"
            }, 
            {
                "arrival_airport": "Rio de Janeiro, Brazil (SDU-Santos Dumont)", 
                "arrival_time": "6:25pm", 
                "departure_airport": "Sao Paulo, Brazil (GRU-Guarulhos - Governor Andre Franco Montoro Intl.)", 
                "departure_time": "5:25pm"
            }
        ], 
        "ticket price": "1655.53", 
        "airline": "", 
        "carrier_operatedby": ""
    }, 
    {
        "arrival": {
            "airportCode": "GIG", 
            "airportCity": "Rio de Janeiro"
        }, 
        "travel_date": "03/15/18", 
        "flight duration": "1 days 10 hours 3 minutes", 
        "plane": "Boeing 767", 
        "stops": "Nonstop", 
        "total_distance": "4,826 miles", 
        "plane code": "764", 
        "booking_date": "12/18/17", 
        "departure": {
            "airportCode": "JFK", 
            "airportCity": "New York"
        }, 
        "timings": [
            {
                "arrival_airport": "Rio de Janeiro, Brazil (GIG-Galeao - Antonio Carlos Jobim Intl.)", 
                "arrival_time": "10:25am", 
                "departure_airport": "New York, NY (JFK-John F. Kennedy Intl.)", 
                "departure_time": "9:22pm"
            }
        ], 
        "ticket price": "1663.10", 
        "airline": "Delta", 
        "carrier_operatedby": ""
    }, 
    {
        "arrival": {
            "airportCode": "GIG", 
            "airportCity": "Rio de Janeiro"
        }, 
        "travel_date": "03/15/18", 
        "flight duration": "1 days 14 hours 55 minutes", 
        "plane": "Airbus A320", 
        "stops": "1 Stops", 
        "total_distance": "5,510 miles", 
        "plane code": "320", 
        "booking_date": "12/18/17", 
        "departure": {
            "airportCode": "LGA", 
            "airportCity": "New York"
        }, 
        "timings": [
            {
                "arrival_airport": "Atlanta, GA (ATL-Hartsfield-Jackson Atlanta Intl.)", 
                "arrival_time": "7:49pm", 
                "departure_airport": "New York, NY (LGA-LaGuardia)", 
                "departure_time": "5:00pm"
            }, 
            {
                "arrival_airport": "Rio de Janeiro, Brazil (GIG-Galeao - Antonio Carlos Jobim Intl.)", 
                "arrival_time": "10:55am", 
                "departure_airport": "Atlanta, GA (ATL-Hartsfield-Jackson Atlanta Intl.)", 
                "departure_time": "10:25pm"
            }
        ], 
        "ticket price": "1667.60", 
        "airline": "Delta", 
        "carrier_operatedby": ""
    }, 
    {
        "arrival": {
            "airportCode": "GIG", 
            "airportCity": "Rio de Janeiro"
        }, 
        "travel_date": "03/15/18", 
        "flight duration": "1 days 17 hours 25 minutes", 
        "plane": "Boeing 767-300", 
        "stops": "1 Stops", 
        "total_distance": "6,434 miles", 
        "plane code": "763", 
        "booking_date": "12/18/17", 
        "departure": {
            "airportCode": "EWR", 
            "airportCity": "Newark"
        }, 
        "timings": [
            {
                "arrival_airport": "Houston, TX (IAH-George Bush Intercontinental)", 
                "arrival_time": "6:56pm", 
                "departure_airport": "Newark, NJ (EWR-Liberty Intl.)", 
                "departure_time": "3:50pm"
            }, 
            {
                "arrival_airport": "Rio de Janeiro, Brazil (GIG-Galeao - Antonio Carlos Jobim Intl.)", 
                "arrival_time": "12:15pm", 
                "departure_airport": "Houston, TX (IAH-George Bush Intercontinental)", 
                "departure_time": "9:40pm"
            }
        ], 
        "ticket price": "1667.60", 
        "airline": "United", 
        "carrier_operatedby": ""
    }, 
    {
        "arrival": {
            "airportCode": "GIG", 
            "airportCity": "Rio de Janeiro"
        }, 
        "travel_date": "03/15/18", 
        "flight duration": "1 days 16 hours 5 minutes", 
        "plane": "Boeing 777", 
        "stops": "1 Stops", 
        "total_distance": "6,434 miles", 
        "plane code": "777", 
        "booking_date": "12/18/17", 
        "departure": {
            "airportCode": "EWR", 
            "airportCity": "Newark"
        }, 
        "timings": [
            {
                "arrival_airport": "Houston, TX (IAH-George Bush Intercontinental)", 
                "arrival_time": "8:06pm", 
                "departure_airport": "Newark, NJ (EWR-Liberty Intl.)", 
                "departure_time": "5:10pm"
            }, 
            {
                "arrival_airport": "Rio de Janeiro, Brazil (GIG-Galeao - Antonio Carlos Jobim Intl.)", 
                "arrival_time": "12:15pm", 
                "departure_airport": "Houston, TX (IAH-George Bush Intercontinental)", 
                "departure_time": "9:40pm"
            }
        ], 
        "ticket price": "1667.60", 
        "airline": "United", 
        "carrier_operatedby": ""
    }, 
    {
        "arrival": {
            "airportCode": "GIG", 
            "airportCity": "Rio de Janeiro"
        }, 
        "travel_date": "03/15/18", 
        "flight duration": "1 days 14 hours 55 minutes", 
        "plane": "Boeing 717", 
        "stops": "1 Stops", 
        "total_distance": "5,510 miles", 
        "plane code": "717", 
        "booking_date": "12/18/17", 
        "departure": {
            "airportCode": "JFK", 
            "airportCity": "New York"
        }, 
        "timings": [
            {
                "arrival_airport": "Atlanta, GA (ATL-Hartsfield-Jackson Atlanta Intl.)", 
                "arrival_time": "7:55pm", 
                "departure_airport": "New York, NY (JFK-John F. Kennedy Intl.)", 
                "departure_time": "5:00pm"
            }, 
            {
                "arrival_airport": "Rio de Janeiro, Brazil (GIG-Galeao - Antonio Carlos Jobim Intl.)", 
                "arrival_time": "10:55am", 
                "departure_airport": "Atlanta, GA (ATL-Hartsfield-Jackson Atlanta Intl.)", 
                "departure_time": "10:25pm"
            }
        ], 
        "ticket price": "1667.60", 
        "airline": "Delta", 
        "carrier_operatedby": ""
    }, 
    {
        "arrival": {
            "airportCode": "GIG", 
            "airportCity": "Rio de Janeiro"
        }, 
        "travel_date": "03/15/18", 
        "flight duration": "1 days 13 hours 55 minutes", 
        "plane": "Airbus A320", 
        "stops": "1 Stops", 
        "total_distance": "5,510 miles", 
        "plane code": "320", 
        "booking_date": "12/18/17", 
        "departure": {
            "airportCode": "LGA", 
            "airportCity": "New York"
        }, 
        "timings": [
            {
                "arrival_airport": "Atlanta, GA (ATL-Hartsfield-Jackson Atlanta Intl.)", 
                "arrival_time": "8:45pm", 
                "departure_airport": "New York, NY (LGA-LaGuardia)", 
                "departure_time": "6:00pm"
            }, 
            {
                "arrival_airport": "Rio de Janeiro, Brazil (GIG-Galeao - Antonio Carlos Jobim Intl.)", 
                "arrival_time": "10:55am", 
                "departure_airport": "Atlanta, GA (ATL-Hartsfield-Jackson Atlanta Intl.)", 
                "departure_time": "10:25pm"
            }
        ], 
        "ticket price": "1667.60", 
        "airline": "Delta", 
        "carrier_operatedby": ""
    }, 
    {
        "arrival": {
            "airportCode": "GIG", 
            "airportCity": "Rio de Janeiro"
        }, 
        "travel_date": "03/15/18", 
        "flight duration": "1 days 16 hours 6 minutes", 
        "plane": "Boeing 737-800", 
        "stops": "1 Stops", 
        "total_distance": "6,434 miles", 
        "plane code": "738", 
        "booking_date": "12/18/17", 
        "departure": {
            "airportCode": "LGA", 
            "airportCity": "New York"
        }, 
        "timings": [
            {
                "arrival_airport": "Houston, TX (IAH-George Bush Intercontinental)", 
                "arrival_time": "8:24pm", 
                "departure_airport": "New York, NY (LGA-LaGuardia)", 
                "departure_time": "5:09pm"
            }, 
            {
                "arrival_airport": "Rio de Janeiro, Brazil (GIG-Galeao - Antonio Carlos Jobim Intl.)", 
                "arrival_time": "12:15pm", 
                "departure_airport": "Houston, TX (IAH-George Bush Intercontinental)", 
                "departure_time": "9:40pm"
            }
        ], 
        "ticket price": "1667.60", 
        "airline": "United", 
        "carrier_operatedby": ""
    }, 
    {
        "arrival": {
            "airportCode": "GIG", 
            "airportCity": "Rio de Janeiro"
        }, 
        "travel_date": "03/15/18", 
        "flight duration": "1 days 19 hours 2 minutes", 
        "plane": "Boeing 737-800", 
        "stops": "1 Stops", 
        "total_distance": "6,434 miles", 
        "plane code": "738", 
        "booking_date": "12/18/17", 
        "departure": {
            "airportCode": "EWR", 
            "airportCity": "Newark"
        }, 
        "timings": [
            {
                "arrival_airport": "Houston, TX (IAH-George Bush Intercontinental)", 
                "arrival_time": "5:22pm", 
                "departure_airport": "Newark, NJ (EWR-Liberty Intl.)", 
                "departure_time": "2:13pm"
            }, 
            {
                "arrival_airport": "Rio de Janeiro, Brazil (GIG-Galeao - Antonio Carlos Jobim Intl.)", 
                "arrival_time": "12:15pm", 
                "departure_airport": "Houston, TX (IAH-George Bush Intercontinental)", 
                "departure_time": "9:40pm"
            }
        ], 
        "ticket price": "1667.60", 
        "airline": "United", 
        "carrier_operatedby": ""
    }, 
    {
        "arrival": {
            "airportCode": "GIG", 
            "airportCity": "Rio de Janeiro"
        }, 
        "travel_date": "03/15/18", 
        "flight duration": "1 days 16 hours 30 minutes", 
        "plane": "Airbus A319", 
        "stops": "1 Stops", 
        "total_distance": "5,510 miles", 
        "plane code": "319", 
        "booking_date": "12/18/17", 
        "departure": {
            "airportCode": "JFK", 
            "airportCity": "New York"
        }, 
        "timings": [
            {
                "arrival_airport": "Atlanta, GA (ATL-Hartsfield-Jackson Atlanta Intl.)", 
                "arrival_time": "6:20pm", 
                "departure_airport": "New York, NY (JFK-John F. Kennedy Intl.)", 
                "departure_time": "3:25pm"
            }, 
            {
                "arrival_airport": "Rio de Janeiro, Brazil (GIG-Galeao - Antonio Carlos Jobim Intl.)", 
                "arrival_time": "10:55am", 
                "departure_airport": "Atlanta, GA (ATL-Hartsfield-Jackson Atlanta Intl.)", 
                "departure_time": "10:25pm"
            }
        ], 
        "ticket price": "1667.60", 
        "airline": "Delta", 
        "carrier_operatedby": ""
    }, 
    {
        "arrival": {
            "airportCode": "GIG", 
            "airportCity": "Rio de Janeiro"
        }, 
        "travel_date": "03/15/18", 
        "flight duration": "1 days 18 hours 55 minutes", 
        "plane": "Airbus A320", 
        "stops": "1 Stops", 
        "total_distance": "5,510 miles", 
        "plane code": "320", 
        "booking_date": "12/18/17", 
        "departure": {
            "airportCode": "LGA", 
            "airportCity": "New York"
        }, 
        "timings": [
            {
                "arrival_airport": "Atlanta, GA (ATL-Hartsfield-Jackson Atlanta Intl.)", 
                "arrival_time": "3:44pm", 
                "departure_airport": "New York, NY (LGA-LaGuardia)", 
                "departure_time": "1:00pm"
            }, 
            {
                "arrival_airport": "Rio de Janeiro, Brazil (GIG-Galeao - Antonio Carlos Jobim Intl.)", 
                "arrival_time": "10:55am", 
                "departure_airport": "Atlanta, GA (ATL-Hartsfield-Jackson Atlanta Intl.)", 
                "departure_time": "10:25pm"
            }
        ], 
        "ticket price": "1667.60", 
        "airline": "Delta", 
        "carrier_operatedby": ""
    }, 
    {
        "arrival": {
            "airportCode": "GIG", 
            "airportCity": "Rio de Janeiro"
        }, 
        "travel_date": "03/15/18", 
        "flight duration": "1 days 17 hours 55 minutes", 
        "plane": "Boeing 737-800", 
        "stops": "1 Stops", 
        "total_distance": "5,510 miles", 
        "plane code": "738", 
        "booking_date": "12/18/17", 
        "departure": {
            "airportCode": "LGA", 
            "airportCity": "New York"
        }, 
        "timings": [
            {
                "arrival_airport": "Atlanta, GA (ATL-Hartsfield-Jackson Atlanta Intl.)", 
                "arrival_time": "4:45pm", 
                "departure_airport": "New York, NY (LGA-LaGuardia)", 
                "departure_time": "2:00pm"
            }, 
            {
                "arrival_airport": "Rio de Janeiro, Brazil (GIG-Galeao - Antonio Carlos Jobim Intl.)", 
                "arrival_time": "10:55am", 
                "departure_airport": "Atlanta, GA (ATL-Hartsfield-Jackson Atlanta Intl.)", 
                "departure_time": "10:25pm"
            }
        ], 
        "ticket price": "1667.60", 
        "airline": "Delta", 
        "carrier_operatedby": ""
    }, 
    {
        "arrival": {
            "airportCode": "GIG", 
            "airportCity": "Rio de Janeiro"
        }, 
        "travel_date": "03/15/18", 
        "flight duration": "1 days 19 hours 55 minutes", 
        "plane": "Airbus A320", 
        "stops": "1 Stops", 
        "total_distance": "5,510 miles", 
        "plane code": "320", 
        "booking_date": "12/18/17", 
        "departure": {
            "airportCode": "LGA", 
            "airportCity": "New York"
        }, 
        "timings": [
            {
                "arrival_airport": "Atlanta, GA (ATL-Hartsfield-Jackson Atlanta Intl.)", 
                "arrival_time": "2:46pm", 
                "departure_airport": "New York, NY (LGA-LaGuardia)", 
                "departure_time": "12:00pm"
            }, 
            {
                "arrival_airport": "Rio de Janeiro, Brazil (GIG-Galeao - Antonio Carlos Jobim Intl.)", 
                "arrival_time": "10:55am", 
                "departure_airport": "Atlanta, GA (ATL-Hartsfield-Jackson Atlanta Intl.)", 
                "departure_time": "10:25pm"
            }
        ], 
        "ticket price": "1667.60", 
        "airline": "Delta", 
        "carrier_operatedby": ""
    }, 
    {
        "arrival": {
            "airportCode": "GIG", 
            "airportCity": "Rio de Janeiro"
        }, 
        "travel_date": "03/15/18", 
        "flight duration": "1 days 18 hours 55 minutes", 
        "plane": "Boeing 717", 
        "stops": "1 Stops", 
        "total_distance": "5,510 miles", 
        "plane code": "717", 
        "booking_date": "12/18/17", 
        "departure": {
            "airportCode": "EWR", 
            "airportCity": "Newark"
        }, 
        "timings": [
            {
                "arrival_airport": "Atlanta, GA (ATL-Hartsfield-Jackson Atlanta Intl.)", 
                "arrival_time": "3:39pm", 
                "departure_airport": "Newark, NJ (EWR-Liberty Intl.)", 
                "departure_time": "1:00pm"
            }, 
            {
                "arrival_airport": "Rio de Janeiro, Brazil (GIG-Galeao - Antonio Carlos Jobim Intl.)", 
                "arrival_time": "10:55am", 
                "departure_airport": "Atlanta, GA (ATL-Hartsfield-Jackson Atlanta Intl.)", 
                "departure_time": "10:25pm"
            }
        ], 
        "ticket price": "1667.60", 
        "airline": "Delta", 
        "carrier_operatedby": ""
    }, 
    {
        "arrival": {
            "airportCode": "GIG", 
            "airportCity": "Rio de Janeiro"
        }, 
        "travel_date": "03/15/18", 
        "flight duration": "1 days 14 hours 13 minutes", 
        "plane": "Boeing 717", 
        "stops": "1 Stops", 
        "total_distance": "5,510 miles", 
        "plane code": "717", 
        "booking_date": "12/18/17", 
        "departure": {
            "airportCode": "EWR", 
            "airportCity": "Newark"
        }, 
        "timings": [
            {
                "arrival_airport": "Atlanta, GA (ATL-Hartsfield-Jackson Atlanta Intl.)", 
                "arrival_time": "8:24pm", 
                "departure_airport": "Newark, NJ (EWR-Liberty Intl.)", 
                "departure_time": "5:42pm"
            }, 
            {
                "arrival_airport": "Rio de Janeiro, Brazil (GIG-Galeao - Antonio Carlos Jobim Intl.)", 
                "arrival_time": "10:55am", 
                "departure_airport": "Atlanta, GA (ATL-Hartsfield-Jackson Atlanta Intl.)", 
                "departure_time": "10:25pm"
            }
        ], 
        "ticket price": "1667.60", 
        "airline": "Delta", 
        "carrier_operatedby": ""
    }, 
    {
        "arrival": {
            "airportCode": "GIG", 
            "airportCity": "Rio de Janeiro"
        }, 
        "travel_date": "03/15/18", 
        "flight duration": "1 days 18 hours 20 minutes", 
        "plane": "Airbus A319", 
        "stops": "1 Stops", 
        "total_distance": "5,510 miles", 
        "plane code": "319", 
        "booking_date": "12/18/17", 
        "departure": {
            "airportCode": "JFK", 
            "airportCity": "New York"
        }, 
        "timings": [
            {
                "arrival_airport": "Atlanta, GA (ATL-Hartsfield-Jackson Atlanta Intl.)", 
                "arrival_time": "4:19pm", 
                "departure_airport": "New York, NY (JFK-John F. Kennedy Intl.)", 
                "departure_time": "1:35pm"
            }, 
            {
                "arrival_airport": "Rio de Janeiro, Brazil (GIG-Galeao - Antonio Carlos Jobim Intl.)", 
                "arrival_time": "10:55am", 
                "departure_airport": "Atlanta, GA (ATL-Hartsfield-Jackson Atlanta Intl.)", 
                "departure_time": "10:25pm"
            }
        ], 
        "ticket price": "1667.60", 
        "airline": "Delta", 
        "carrier_operatedby": ""
    }, 
    {
        "arrival": {
            "airportCode": "GIG", 
            "airportCity": "Rio de Janeiro"
        }, 
        "travel_date": "03/15/18", 
        "flight duration": "1 days 14 hours 25 minutes", 
        "plane": "Boeing 737-800", 
        "stops": "1 Stops", 
        "total_distance": "5,510 miles", 
        "plane code": "738", 
        "booking_date": "12/18/17", 
        "departure": {
            "airportCode": "LGA", 
            "airportCity": "New York"
        }, 
        "timings": [
            {
                "arrival_airport": "Atlanta, GA (ATL-Hartsfield-Jackson Atlanta Intl.)", 
                "arrival_time": "8:18pm", 
                "departure_airport": "New York, NY (LGA-LaGuardia)", 
                "departure_time": "5:30pm"
            }, 
            {
                "arrival_airport": "Rio de Janeiro, Brazil (GIG-Galeao - Antonio Carlos Jobim Intl.)", 
                "arrival_time": "10:55am", 
                "departure_airport": "Atlanta, GA (ATL-Hartsfield-Jackson Atlanta Intl.)", 
                "departure_time": "10:25pm"
            }
        ], 
        "ticket price": "1667.60", 
        "airline": "Delta", 
        "carrier_operatedby": ""
    }, 
    {
        "arrival": {
            "airportCode": "GIG", 
            "airportCity": "Rio de Janeiro"
        }, 
        "travel_date": "03/15/18", 
        "flight duration": "1 days 17 hours 33 minutes", 
        "plane": "Boeing 737-900", 
        "stops": "1 Stops", 
        "total_distance": "6,434 miles", 
        "plane code": "739", 
        "booking_date": "12/18/17", 
        "departure": {
            "airportCode": "LGA", 
            "airportCity": "New York"
        }, 
        "timings": [
            {
                "arrival_airport": "Houston, TX (IAH-George Bush Intercontinental)", 
                "arrival_time": "6:57pm", 
                "departure_airport": "New York, NY (LGA-LaGuardia)", 
                "departure_time": "3:42pm"
            }, 
            {
                "arrival_airport": "Rio de Janeiro, Brazil (GIG-Galeao - Antonio Carlos Jobim Intl.)", 
                "arrival_time": "12:15pm", 
                "departure_airport": "Houston, TX (IAH-George Bush Intercontinental)", 
                "departure_time": "9:40pm"
            }
        ], 
        "ticket price": "1667.60", 
        "airline": "United", 
        "carrier_operatedby": ""
    }, 
    {
        "arrival": {
            "airportCode": "GIG", 
            "airportCity": "Rio de Janeiro"
        }, 
        "travel_date": "03/15/18", 
        "flight duration": "1 days 16 hours 10 minutes", 
        "plane": "Boeing 717", 
        "stops": "1 Stops", 
        "total_distance": "5,510 miles", 
        "plane code": "717", 
        "booking_date": "12/18/17", 
        "departure": {
            "airportCode": "EWR", 
            "airportCity": "Newark"
        }, 
        "timings": [
            {
                "arrival_airport": "Atlanta, GA (ATL-Hartsfield-Jackson Atlanta Intl.)", 
                "arrival_time": "6:25pm", 
                "departure_airport": "Newark, NJ (EWR-Liberty Intl.)", 
                "departure_time": "3:45pm"
            }, 
            {
                "arrival_airport": "Rio de Janeiro, Brazil (GIG-Galeao - Antonio Carlos Jobim Intl.)", 
                "arrival_time": "10:55am", 
                "departure_airport": "Atlanta, GA (ATL-Hartsfield-Jackson Atlanta Intl.)", 
                "departure_time": "10:25pm"
            }
        ], 
        "ticket price": "1667.60", 
        "airline": "Delta", 
        "carrier_operatedby": ""
    }, 
    {
        "arrival": {
            "airportCode": "SDU", 
            "airportCity": "Rio de Janeiro"
        }, 
        "travel_date": "03/15/18", 
        "flight duration": "1 days 12 hours 40 minutes", 
        "plane": "AIRBUS INDUSTRIE A330-300", 
        "stops": "1 Stops", 
        "total_distance": "4,989 miles", 
        "plane code": "333", 
        "booking_date": "12/18/17", 
        "departure": {
            "airportCode": "JFK", 
            "airportCity": "New York"
        }, 
        "timings": [
            {
                "arrival_airport": "Sao Paulo, Brazil (GRU-Guarulhos - Governor Andre Franco Montoro Intl.)", 
                "arrival_time": "8:20am", 
                "departure_airport": "New York, NY (JFK-John F. Kennedy Intl.)", 
                "departure_time": "7:35pm"
            }, 
            {
                "arrival_airport": "Rio de Janeiro, Brazil (SDU-Santos Dumont)", 
                "arrival_time": "11:15am", 
                "departure_airport": "Sao Paulo, Brazil (GRU-Guarulhos - Governor Andre Franco Montoro Intl.)", 
                "departure_time": "10:15am"
            }
        ], 
        "ticket price": "1672.00", 
        "airline": "Delta", 
        "carrier_operatedby": ""
    }, 
    {
        "arrival": {
            "airportCode": "SDU", 
            "airportCity": "Rio de Janeiro"
        }, 
        "travel_date": "03/15/18", 
        "flight duration": "1 days 14 hours 0 minutes", 
        "plane": "Boeing 777", 
        "stops": "1 Stops", 
        "total_distance": "4,989 miles", 
        "plane code": "777", 
        "booking_date": "12/18/17", 
        "departure": {
            "airportCode": "EWR", 
            "airportCity": "Newark"
        }, 
        "timings": [
            {
                "arrival_airport": "Sao Paulo, Brazil (GRU-Guarulhos - Governor Andre Franco Montoro Intl.)", 
                "arrival_time": "10:40am", 
                "departure_airport": "Newark, NJ (EWR-Liberty Intl.)", 
                "departure_time": "9:40pm"
            }, 
            {
                "arrival_airport": "Rio de Janeiro, Brazil (SDU-Santos Dumont)", 
                "arrival_time": "2:40pm", 
                "departure_airport": "Sao Paulo, Brazil (GRU-Guarulhos - Governor Andre Franco Montoro Intl.)", 
                "departure_time": "1:45pm"
            }
        ], 
        "ticket price": "1672.00", 
        "airline": "Azul", 
        "carrier_operatedby": "United"
    }, 
    {
        "arrival": {
            "airportCode": "SDU", 
            "airportCity": "Rio de Janeiro"
        }, 
        "travel_date": "03/15/18", 
        "flight duration": "1 days 20 hours 25 minutes", 
        "plane": "Boeing 777", 
        "stops": "1 Stops", 
        "total_distance": "4,989 miles", 
        "plane code": "777", 
        "booking_date": "12/18/17", 
        "departure": {
            "airportCode": "EWR", 
            "airportCity": "Newark"
        }, 
        "timings": [
            {
                "arrival_airport": "Sao Paulo, Brazil (GRU-Guarulhos - Governor Andre Franco Montoro Intl.)", 
                "arrival_time": "10:40am", 
                "departure_airport": "Newark, NJ (EWR-Liberty Intl.)", 
                "departure_time": "9:40pm"
            }, 
            {
                "arrival_airport": "Rio de Janeiro, Brazil (SDU-Santos Dumont)", 
                "arrival_time": "9:05pm", 
                "departure_airport": "Sao Paulo, Brazil (GRU-Guarulhos - Governor Andre Franco Montoro Intl.)", 
                "departure_time": "8:05pm"
            }
        ], 
        "ticket price": "1672.00", 
        "airline": "Azul", 
        "carrier_operatedby": "United"
    }, 
    {
        "arrival": {
            "airportCode": "SDU", 
            "airportCity": "Rio de Janeiro"
        }, 
        "travel_date": "03/15/18", 
        "flight duration": "1 days 14 hours 0 minutes", 
        "plane": "Boeing 777", 
        "stops": "1 Stops", 
        "total_distance": "4,989 miles", 
        "plane code": "777", 
        "booking_date": "12/18/17", 
        "departure": {
            "airportCode": "EWR", 
            "airportCity": "Newark"
        }, 
        "timings": [
            {
                "arrival_airport": "Sao Paulo, Brazil (GRU-Guarulhos - Governor Andre Franco Montoro Intl.)", 
                "arrival_time": "10:40am", 
                "departure_airport": "Newark, NJ (EWR-Liberty Intl.)", 
                "departure_time": "9:40pm"
            }, 
            {
                "arrival_airport": "Rio de Janeiro, Brazil (SDU-Santos Dumont)", 
                "arrival_time": "2:40pm", 
                "departure_airport": "Sao Paulo, Brazil (GRU-Guarulhos - Governor Andre Franco Montoro Intl.)", 
                "departure_time": "1:45pm"
            }
        ], 
        "ticket price": "1679.00", 
        "airline": "", 
        "carrier_operatedby": ""
    }
]